[
    {"soru": "Haccın farzları (rükünleri) kaç tanedir?", "siklar": ["3", "4", "5", "7"], "cevap": "3"},
    {"soru": "Aşağıdakilerden hangisi haccın farzlarından biri değildir?", "siklar": ["Şeytan taşlamak", "İhram", "Arafat vakfesi", "Ziyaret tavafı"], "cevap": "Şeytan taşlamak"},
    {"soru": "Hac veya umre yapmaya niyet eden kişinin, diğer zamanlarda helal olan bazı fiilleri kendisine haram kılmasına ne denir?", "siklar": ["İhram", "Vakfe", "Tavaf", "Sa'y"], "cevap": "İhram"},
    {"soru": "Kabe'nin etrafında bir kez dönmeye ne ad verilir?", "siklar": ["Şavt", "Tavaf", "Vakfe", "Hacerü'l-Esved"], "cevap": "Şavt"},
    {"soru": "Kabe'nin etrafında yedi şavt (dönüş) yapmaya ne ad verilir?", "siklar": ["Tavaf", "Sa'y", "Vakfe", "Remiy"], "cevap": "Tavaf"},
    {"soru": "Hac ve umre yolcularının ihrama girmek zorunda oldukları sınır bölgelerine ne denir?", "siklar": ["Mikat", "Mina", "Müzdelife", "Harem"], "cevap": "Mikat"},
    {"soru": "Hac ibadeti hangi İslami aylarda yapılır?", "siklar": ["Şevval, Zilkade ve Zilhicce", "Ramazan", "Recep", "Muharrem"], "cevap": "Şevval, Zilkade ve Zilhicce"},
    {"soru": "Arafat vakfesi ne zaman yapılır?", "siklar": ["Arefe günü", "Bayramın birinci günü", "Zilhicce'nin ilk günü", "Kandil gecesi"], "cevap": "Arefe günü"},
    {"soru": "Safa ile Merve tepeleri arasında 4 gidiş 3 geliş olmak üzere yapılan yürüyüşe ne denir?", "siklar": ["Sa'y", "Tavaf", "Vakfe", "İstila"], "cevap": "Sa'y"},
    {"soru": "Hacda 'Vakfe' ibadeti nerede yapılırsa haccın farzı yerine gelmiş olur?", "siklar": ["Arafat", "Mina", "Müzdelife", "Safa"], "cevap": "Arafat"},
    {"soru": "Sadece hac yapmak niyetiyle ihrama girilen hac türüne ne denir?", "siklar": ["İfrad Haccı", "Temettu Haccı", "Kıran Haccı", "Umre"], "cevap": "İfrad Haccı"},
    {"soru": "Aynı yıl içinde önce umre yapıp ihramdan çıkan, sonra tekrar hac için ihrama girilen hac türü?", "siklar": ["Temettu Haccı", "İfrad Haccı", "Kıran Haccı", "Bedel Haccı"], "cevap": "Temettu Haccı"},
    {"soru": "Hem hac hem umreye aynı ihramla niyet edilerek yapılan hac türü hangisidir?", "siklar": ["Kıran Haccı", "İfrad Haccı", "Temettu Haccı", "Kaza Haccı"], "cevap": "Kıran Haccı"},
    {"soru": "İhrama girerken okunan 'Lebbeyk Allahümme Lebbeyk...' duasının adı nedir?", "siklar": ["Telbiye", "Tekbir", "Tehlil", "Tahmid"], "cevap": "Telbiye"},
    {"soru": "Kabe'de tavafın başladığı ve bittiği yer olan siyah taşın adı nedir?", "siklar": ["Hacerü'l-Esved", "Makam-ı İbrahim", "Hicr-i İsmail", "Mültezem"], "cevap": "Hacerü'l-Esved"},
    {"soru": "Tavaf sırasında Hacerü'l-Esved'i selamlamaya ne denir?", "siklar": ["İstila", "Remel", "Iztıba", "Hervele"], "cevap": "İstila"},
    {"soru": "Erkeklerin tavafın ilk üç şavtında omuzlarını sallayarak çalımlı yürümesine ne denir?", "siklar": ["Remel", "Hervele", "Iztıba", "Sa'y"], "cevap": "Remel"},
    {"soru": "Sa'y yaparken yeşil direkler arasında hızlıca koşmaya ne denir?", "siklar": ["Hervele", "Remel", "Iztıba", "Vakfe"], "cevap": "Hervele"},
    {"soru": "Arefe gününü bayram gününe bağlayan gece Arafat'tan sonra nerede vakfe yapılır?", "siklar": ["Müzdelife", "Mina", "Cemerat", "Mikat"], "cevap": "Müzdelife"},
    {"soru": "Şeytan taşlama (Cemerat) ibadeti nerede gerçekleştirilir?", "siklar": ["Mina", "Müzdelife", "Arafat", "Kudüs"], "cevap": "Mina"},
    {"soru": "Hacda kurban kesilen yer hangisidir?", "siklar": ["Mina", "Arafat", "Müzdelife", "Mekke merkezi"], "cevap": "Mina"},
    {"soru": "Haccın vaciplerinden olan 'Sa'y' hangi tepeler arasında yapılır?", "siklar": ["Safa - Merve", "Uhud - Nur", "Hira - Sevr", "Arafat - Mina"], "cevap": "Safa - Merve"},
    {"soru": "Kabe'nin çevresindeki kapalı alana ne ad verilir?", "siklar": ["Mescid-i Haram", "Mescid-i Aksa", "Mescid-i Nebevi", "Kuba Mescidi"], "cevap": "Mescid-i Haram"},
    {"soru": "Mekke dışından gelenlerin (Afakilerin) Mekke'ye vardıklarında yaptıkları ilk tavaf?", "siklar": ["Kudüm Tavafı", "Ziyaret Tavafı", "Veda Tavafı", "Umre Tavafı"], "cevap": "Kudüm Tavafı"},
    {"soru": "Mekke'den ayrılırken yapılan son tavafa ne denir?", "siklar": ["Veda Tavafı", "Kudüm Tavafı", "Ziyaret Tavafı", "Kudüs Tavafı"], "cevap": "Veda Tavafı"},
    {"soru": "Umrenin kaç farzı vardır?", "siklar": ["2 (İhram ve Tavaf)", "3", "4", "5"], "cevap": "2 (İhram ve Tavaf)"},
    {"soru": "Umre ile hac arasındaki en temel fark nedir?", "siklar": ["Umrede Arafat vakfesi ve kurban yoktur", "Umre farzdır", "Hac her zaman yapılır", "Umrede tavaf yoktur"], "cevap": "Umrede Arafat vakfesi ve kurban yoktur"},
    {"soru": "İhramlı kişinin saçını kesmesi veya tıraş olması neyi gerektirir?", "siklar": ["Ceza (Kurban veya sadaka)", "Haccın bozulmasını", "Namazın bozulmasını", "Fidye gerektirmez"], "cevap": "Ceza (Kurban veya sadaka)"},
    {"soru": "Hacda şeytan taşlarken toplamda kaç taş atılır (4 gün sonunda)?", "siklar": ["70", "49", "21", "100"], "cevap": "70"},
    {"soru": "Arafat'ta öğle ve ikindi namazlarının birleştirilerek kılınmasına ne denir?", "siklar": ["Cem-i Takdim", "Cem-i Tehir", "Kasr-ı Salat", "Cuma namazı"], "cevap": "Cem-i Takdim"},
    {"soru": "Müzdelife'de akşam ve yatsı namazlarının birleştirilerek kılınmasına ne denir?", "siklar": ["Cem-i Tehir", "Cem-i Takdim", "İstiska", "Küsuf"], "cevap": "Cem-i Tehir"},
    {"soru": "Mekke'de bulunan ve içinde Hz. İbrahim'in ayak izinin bulunduğu taşın adı?", "siklar": ["Makam-ı İbrahim", "Hacerü'l-Esved", "Hicr-i İsmail", "Rükn-i Yemani"], "cevap": "Makam-ı İbrahim"},
    {"soru": "Kabe'nin yanında bulunan ve kutsal sayılan suyun adı nedir?", "siklar": ["Zemzem", "Kevser", "Selsebil", "Nil"], "cevap": "Zemzem"},
    {"soru": "Zemzem suyunu içen Hz. Hacer ve oğlu kimdir?", "siklar": ["Hz. İsmail", "Hz. İshak", "Hz. Yusuf", "Hz. Yakub"], "cevap": "Hz. İsmail"},
    {"soru": "Kabe'nin kuzey tarafında bulunan yarım daire şeklindeki duvara ne denir?", "siklar": ["Hicr-i İsmail (Hatîm)", "Mültezem", "Kıble", "Minber"], "cevap": "Hicr-i İsmail (Hatîm)"},
    {"soru": "Peygamber Efendimiz (s.a.v) kaç kez hac yapmıştır?", "siklar": ["1", "2", "3", "4"], "cevap": "1"},
    {"soru": "Peygamberimizin yaptığı haccın özel adı nedir?", "siklar": ["Veda Haccı", "İlk Hac", "Hacc-ı Ekber", "Hacc-ı Mebrur"], "cevap": "Veda Haccı"},
    {"soru": "Ziyaret tavafının vakti ne zaman başlar?", "siklar": ["Bayramın 1. günü şafak vaktinden itibaren", "Arefe günü", "Zilhicce 1'de", "Ramazan'da"], "cevap": "Bayramın 1. günü şafak vaktinden itibaren"},
    {"soru": "Haccın farzlarından 'İhram' neyin şartıdır?", "siklar": ["Haccın geçerlilik şartı", "Namazın şartı", "Zekatın şartı", "Orucun şartı"], "cevap": "Haccın geçerlilik şartı"},
    {"soru": "Hac kelimesinin sözlük anlamı nedir?", "siklar": ["Yönelmek, kastetmek, ziyaret etmek", "Aç kalmak", "Dönmek", "Yürümek"], "cevap": "Yönelmek, kastetmek, ziyaret etmek"},
    {"soru": "Müslümanların haccı bizzat yapamayacak kadar hasta olmaları durumunda yerlerine başkasını göndermelerine ne denir?", "siklar": ["Hac Bedeli (Vekalet)", "Hac Borcu", "Hac Yardımı", "Hac Kefareti"], "cevap": "Hac Bedeli (Vekalet)"},
    {"soru": "Hac ibadeti kimlere farzdır?", "siklar": ["Akıllı, ergen ve imkanı olan tüm müslümanlara", "Sadece yaşlılara", "Sadece erkeklere", "Sadece Araplara"], "cevap": "Akıllı, ergen ve imkanı olan tüm müslümanlara"},
    {"soru": "İhramlıyken yasak olan 'Refes' ne demektir?", "siklar": ["Cinsel içerikli konuşma ve davranışlar", "Kavga etmek", "Günah işlemek", "Yalan söylemek"], "cevap": "Cinsel içerikli konuşma ve davranışlar"},
    {"soru": "Haccın rükünlerinden (farzlarından) birini terk eden kişinin haccı ne olur?", "siklar": ["Geçersiz olur", "Kaza gerekir", "Kurbanla düzelir", "Günah olur ama geçerlidir"], "cevap": "Geçersiz olur"},
    {"soru": "Hacda 'Halk' ve 'Taksir' ne anlama gelir?", "siklar": ["Saçları tamamen kazıtmak veya kısaltmak", "Su içmek", "Yemek yemek", "Tavaf etmek"], "cevap": "Saçları tamamen kazıtmak veya kısaltmak"},
    {"soru": "Mekke'de bulunan Nur Dağı'ndaki Hira Mağarası'nın önemi nedir?", "siklar": ["İlk vahyin geldiği yerdir", "Hicret yolunda saklanılan yerdir", "Haccın başlangıç yeridir", "Kurban kesilen yerdir"], "cevap": "İlk vahyin geldiği yerdir"},
    {"soru": "Medine'ye giden hacıların ziyaret ettiği Peygamberimizin kabrinin bulunduğu yer?", "siklar": ["Ravza-i Mutahhara", "Baki Mezarlığı", "Uhud Şehitliği", "Kuba Mescidi"], "cevap": "Ravza-i Mutahhara"},
    {"soru": "Kabe'nin köşelerinden biri olan ve Yemen tarafına bakan köşenin adı?", "siklar": ["Rükn-i Yemani", "Rükn-i Iraki", "Rükn-i Şami", "Hacerü'l-Esved"], "cevap": "Rükn-i Yemani"},
    {"soru": "Hacıların Mekke'de kaldığı ve ibadet ettiği kutsal bölgenin genel adı?", "siklar": ["Harem Bölgesi", "Hil Bölgesi", "Mikat Bölgesi", "Arafat Bölgesi"], "cevap": "Harem Bölgesi"},
    {"soru": "İhrama giren kişinin giydiği dikişsiz iki parça kumaşa ne denir?", "siklar": ["İzar ve Rida", "Cübbe", "Kaftan", "Entari"], "cevap": "İzar ve Rida"},
    {"soru": "Umre ibadeti yılın hangi zamanında yapılır?", "siklar": ["Hac günleri hariç her zaman", "Sadece Ramazan'da", "Sadece Kurban bayramında", "Sadece Cuma günleri"], "cevap": "Hac günleri hariç her zaman"},
    {"soru": "Hacda Müzdelife vakfesi ne zaman yapılır?", "siklar": ["Arefe gününü bayramın ilk gününe bağlayan gece", "Bayramın 2. günü", "Zilhicce'nin 10. günü öğleden sonra", "Ramazan'da"], "cevap": "Arefe gününü bayramın ilk gününe bağlayan gece"},
    {"soru": "Arafat vakfesinin rüknü nedir?", "siklar": ["Belirlenen vakitte Arafat sınırları içinde bulunmak", "Dua etmek", "Ağlamak", "Oruç tutmak"], "cevap": "Belirlenen vakitte Arafat sınırları içinde bulunmak"},
    {"soru": "Hacda kesilen kurbanlara genel olarak ne ad verilir?", "siklar": ["Hedy", "Udhuye", "Akika", "Adak"], "cevap": "Hedy"},
    {"soru": "Tavaf bittikten sonra Makam-ı İbrahim'in arkasında kılınan namaz?", "siklar": ["Tavaf Namazı", "Şükür Namazı", "Tahiyyetü'l-Mescid", "Hacet Namazı"], "cevap": "Tavaf Namazı"},
    {"soru": "Medine'de inşa edilen İslam tarihinin ilk mescidi hangisidir?", "siklar": ["Kuba Mescidi", "Mescid-i Nebevi", "Mescid-i Kıbleteyn", "Cuma Mescidi"], "cevap": "Kuba Mescidi"},
    {"soru": "Hacda küçük, orta ve büyük şeytanın taşlandığı sütunlara ne denir?", "siklar": ["Cemre", "Mihrap", "Minare", "Sütun"], "cevap": "Cemre"},
    {"soru": "Haccın vaciplerinden olan 'Tıraş olma' işlemi ne zaman yapılır?", "siklar": ["Kurban kesildikten sonra", "Arafat'tan önce", "İhrama girerken", "Mekke'den ayrılırken"], "cevap": "Kurban kesildikten sonra"},
    {"soru": "Umre yapan bir kişi ihramdan ne zaman çıkar?", "siklar": ["Sa'y yaptıktan sonra tıraş olunca", "Tavaf bitince", "Mekke'ye girince", "Medine'ye gidince"], "cevap": "Sa'y yaptıktan sonra tıraş olunca"},
    {"soru": "Mekke ile Medine arası yaklaşık kaç kilometredir?", "siklar": ["450 km", "100 km", "800 km", "250 km"], "cevap": "450 km"},
    {"soru": "Kabe'nin kapısının bulunduğu köşe ile Hacerü'l-Esved arasındaki bölüme ne denir?", "siklar": ["Mültezem", "Hatîm", "Makam", "Rükn-i Şami"], "cevap": "Mültezem"},
    {"soru": "Tavaf ederken Kabe'yi sol tarafa almanın sebebi nedir?", "siklar": ["Peygamberimiz öyle yaptığı için (Sünnet)", "Kural olduğu için", "Kalp Kabe'ye yakın olsun diye", "Hızlı dönmek için"], "cevap": "Peygamberimiz öyle yaptığı için (Sünnet)"},
    {"soru": "Müslümanların birbiriyle tanışması ve kaynaşması haccın hangi yönüdür?", "siklar": ["Sosyal ve evrensel yönü", "Bireysel yönü", "Ekonomik yönü", "Siyasi yönü"], "cevap": "Sosyal ve evrensel yönü"},
    {"soru": "Zengin olup sağlığı yerinde olan birine hac ibadeti ömründe kaç kez farzdır?", "siklar": ["1", "2", "Her yıl", "İsteğe bağlı"], "cevap": "1"},
    {"soru": "İhram yasaklarını ihlal edenlerin ödediği cezai bedele ne denir?", "siklar": ["Dem veya Sadaka", "Zekat", "Fıtır", "Hedy"], "cevap": "Dem veya Sadaka"},
    {"soru": "Hac yolculuğu sırasında Medine'de bulunan Cennetü'l-Baki nedir?", "siklar": ["Sahabelerin defnedildiği mezarlık", "Bir mescit", "Bir pazar yeri", "Bir dağ"], "cevap": "Sahabelerin defnedildiği mezarlık"},
    {"soru": "Kabe'nin örtüsüne ne ad verilir?", "siklar": ["Kisve", "Hırka", "Şal", "Mahfil"], "cevap": "Kisve"},
    {"soru": "Kabe'nin anahtarlarını taşıyan aile hangisidir?", "siklar": ["Şeybi Ailesi", "Haşimoğulları", "Ümeyyeoğulları", "Abbasoğulları"], "cevap": "Şeybi Ailesi"},
    {"soru": "Medine'deki 'Yedi Mescitler' hangi savaşın yapıldığı yerdedir?", "siklar": ["Hendek Savaşı", "Bedir Savaşı", "Uhud Savaşı", "Hayber Savaşı"], "cevap": "Hendek Savaşı"},
    {"soru": "Hacda 'İfaza Tavafı' diğer bir adı nedir?", "siklar": ["Ziyaret Tavafı (Farz olan)", "Veda Tavafı", "Kudüm Tavafı", "Umre Tavafı"], "cevap": "Ziyaret Tavafı (Farz olan)"},
    {"soru": "Hangi durumda hacı adayları 'Sükre' (Kurban) kesmekle yükümlüdür?", "siklar": ["Temettu veya Kıran haccı yapanlar", "İfrad haccı yapanlar", "Sadece umre yapanlar", "Çocuklar"], "cevap": "Temettu veya Kıran haccı yapanlar"},
    {"soru": "Hacerü'l-Esved'i elle selamlamaya veya öpmeye imkan yoksa ne yapılır?", "siklar": ["Uzaktan avuç içlerini Kabe'ye çevirip selamlanır", "Tavaf iptal edilir", "Ağlanır", "Para verilir"], "cevap": "Uzaktan avuç içlerini Kabe'ye çevirip selamlanır"},
    {"soru": "Mekke'de bulunan ve 'Cin Mescidi' olarak bilinen yerin önemi nedir?", "siklar": ["Cinlerin Peygamberimize biat ettiği yerdir", "Kabe'nin ilk yeridir", "Hicretin başladığı yerdir", "Savaş yeridir"], "cevap": "Cinlerin Peygamberimize biat ettiği yerdir"},
    {"soru": "Peygamberimizin 'Burada kılınan bir namaz, diğer mescitlerden bin kat daha hayırlıdır' dediği yer?", "siklar": ["Mescid-i Nebevi", "Mescid-i Aksa", "Kuba Mescidi", "Kıbleteyn Mescidi"], "cevap": "Mescid-i Nebevi"},
    {"soru": "Hac ibadeti sırasında tırnak kesmek ihram yasağı mıdır?", "siklar": ["Evet, yasaktır", "Hayır, serbesttir", "Sadece Arefe günü yasaktır", "Kısaltılabilir"], "cevap": "Evet, yasaktır"},
    {"soru": "Hacda ihramdan çıkmak için 'Saç kazıtmak' mı 'Saç kısaltmak' mı daha faziletlidir?", "siklar": ["Saç kazıtmak (Halk)", "Saç kısaltmak (Taksir)", "İkisi de eşittir", "Fark etmez"], "cevap": "Saç kazıtmak (Halk)"},
    {"soru": "Müzdelife vakfesinin hükmü nedir?", "siklar": ["Vacip", "Farz", "Sünnet", "Müstehap"], "cevap": "Vacip"},
    {"soru": "Hacda Mina'da kalmanın hükmü (genel kabul)?", "siklar": ["Sünnet", "Farz", "Vacip", "Haram"], "cevap": "Sünnet"},
    {"soru": "Tavaf namazı nerede kılınırsa daha iyidir?", "siklar": ["Makam-ı İbrahim'in arkasında", "Mina'da", "Arafat'ta", "Otelde"], "cevap": "Makam-ı İbrahim'in arkasında"},
    {"soru": "Hacca gidemeyenlerin yerine başkasının gitmesi için gerekli olan en temel şart?", "siklar": ["Hacca gitmek isteyen kişinin vefat etmiş veya sürekli hasta olması", "Çok zengin olmak", "Genç olmak", "Hacca gitmek istememek"], "cevap": "Hacca gitmek isteyen kişinin vefat etmiş veya sürekli hasta olması"},
    {"soru": "Hangi ayette haccın insanlara ilan edilmesi emredilir?", "siklar": ["Hac Suresi 27", "Bakara Suresi 197", "Ali İmran Suresi 97", "Maide Suresi 2"], "cevap": "Hac Suresi 27"},
    {"soru": "Hacda Arefe günü akşam namazı nerede kılınır?", "siklar": ["Müzdelife'de yatsı ile birleştirilerek", "Arafat'ta", "Mekke'de", "Mina'da"], "cevap": "Müzdelife'de yatsı ile birleştirilerek"},
    {"soru": "İhrama girerken giyilen kumaşların dikişsiz olmasının sembolik anlamı nedir?", "siklar": ["Ölümü ve mahşeri hatırlatmak (Kefen gibi)", "Hava almak", "Moda", "Temizlik"], "cevap": "Ölümü ve mahşeri hatırlatmak (Kefen gibi)"},
    {"soru": "Peygamberimiz Umre yaparken hangi Mikat yerini kullanmıştır?", "siklar": ["Zülhuleyfe", "Cuhfe", "Karnü'l-Menazil", "Yelemlem"], "cevap": "Zülhuleyfe"},
    {"soru": "İslam'ın beş şartından biri olan hac, Hicretin kaçıncı yılında farz kılınmıştır?", "siklar": ["9. yıl", "2. yıl", "5. yıl", "10. yıl"], "cevap": "9. yıl"},
    {"soru": "Mekke içindeki birinin umre için ihrama girmek üzere gittiği en yakın yer?", "siklar": ["Ten'im (Hz. Ayşe Mescidi)", "Arafat", "Mina", "Medine"], "cevap": "Ten'im (Hz. Ayşe Mescidi)"},
    {"soru": "Hacda Arefe günü güneş batmadan Arafat'tan ayrılmanın cezası nedir?", "siklar": ["Kurban kesmek (Dem)", "Haccın iptali", "Tövbe", "Namaz kılmak"], "cevap": "Kurban kesmek (Dem)"},
    {"soru": "Hac ibadetiyle ilgili 'Lebbeyk' ifadesinin anlamı nedir?", "siklar": ["Buyur Allah'ım, emrine amadeyim", "Allah en büyüktür", "Hamd Allah'adır", "Beni affet"], "cevap": "Buyur Allah'ım, emrine amadeyim"},
    {"soru": "Hacda 'Sa'y' yapmak kimin hatırasını canlandırmaktır?", "siklar": ["Hz. Hacer", "Hz. Amine", "Hz. Hatice", "Hz. Fatıma"], "cevap": "Hz. Hacer"},
    {"soru": "Arafat'ta 'Vakfe' yapmadan direkt Mina'ya giden kişinin haccı ne olur?", "siklar": ["Haccı geçersiz olur", "Haccı tamamdır", "Sadece kurban keser", "Kaza eder"], "cevap": "Haccı geçersiz olur"},
    {"soru": "Hac ibadetinde Kabe'ye yönelerek yapılan duaların kabul edildiği rivayet edilen bölge?", "siklar": ["Mültezem", "Mikat", "Mina", "Müzdelife"], "cevap": "Mültezem"},
    {"soru": "Peygamberimizin 'Hac ...'dır' buyurduğu ibadet?", "siklar": ["Arafat", "Tavaf", "İhlas", "Sabır"], "cevap": "Arafat"},
    {"soru": "İhramlıyken avlanmak veya bitki koparmak yasak mıdır?", "siklar": ["Evet, yasaktır", "Hayır, serbesttir", "Sadece gece yasaktır", "Sadece balık tutulabilir"], "cevap": "Evet, yasaktır"},
    {"soru": "Hacda cemre-i akabe (büyük şeytan) taşlandığında ne yapılır?", "siklar": ["İhramdan çıkmak için ilk adım atılmış olur", "Hac biter", "Mekke'ye dönülür", "Namaz kılınır"], "cevap": "İhramdan çıkmak için ilk adım atılmış olur"},
    {"soru": "Hac yolculuğunda Peygamberimizin doğduğu evi ziyaret etmek haccın şartı mıdır?", "siklar": ["Hayır, ama müstehaptır", "Evet, farzdır", "Evet, vaciptir", "Hayır, yasaktır"], "cevap": "Hayır, ama müstehaptır"},
    {"soru": "Hacda şeytan taşlarken kullanılan taşlar nereden toplanır?", "siklar": ["Müzdelife veya yol boyu", "Arafat", "Kabe'nin içinden", "Cepte getirilir"], "cevap": "Müzdelife veya yol boyu"},
    {"soru": "Hac ibadeti sırasında 'İstişare' ve 'Dayanışma' neyi simgeler?", "siklar": ["İslam kardeşliğini", "Ticareti", "Savaşı", "Yorgunluğu"], "cevap": "İslam kardeşliğini"},
    {"soru": "Umre yapan bir kişi Kurban kesmek zorunda mıdır?", "siklar": ["Hayır, umrede kurban yoktur", "Evet, her umrede vaciptir", "Sadece zenginse", "İsteğe bağlıdır"], "cevap": "Hayır, umrede kurban yoktur"},
    {"soru": "Haccın farzı olan Ziyaret Tavafı bayramdan sonraya bırakılırsa ne gerekir?", "siklar": ["Kurban kesmek gerekir", "Hac iptal olur", "Hiçbir şey gerekmez", "Kaza gerekir"], "cevap": "Kurban kesmek gerekir"},
    {"soru": "İslam'da 'Mebrur bir haccın' karşılığı nedir?", "siklar": ["Cennet", "Dünya malı", "Uzun ömür", "Sağlık"], "cevap": "Cennet"}
]